LICENSE
MANIFEST.in
README.md
manage_net_url.py
requirements.txt
setup.py
net_url/__init__.py
net_url.egg-info/PKG-INFO
net_url.egg-info/SOURCES.txt
net_url.egg-info/dependency_links.txt
net_url.egg-info/entry_points.txt
net_url.egg-info/not-zip-safe
net_url.egg-info/requires.txt
net_url.egg-info/top_level.txt
net_url/src/.rockspec
net_url/src/lua/net/url.lua